macbundler.py
macbundler-0.2.3.dist-info/METADATA
macbundler-0.2.3.dist-info/WHEEL
macbundler-0.2.3.dist-info/entry_points.txt
macbundler-0.2.3.dist-info/licenses/LICENSE
macbundler-0.2.3.dist-info/RECORD
