Metadata-Version: 2.4
Name: macbundler
Version: 0.2.3
Summary: Python tools to create macOS bundles and bundle dynamic libraries.
Project-URL: Homepage, https://github.com/shakfu/macbundler
Project-URL: Repository, https://github.com/shakfu/macbundler
Project-URL: Issues, https://github.com/shakfu/macbundler/issues
Project-URL: Changelog, https://github.com/shakfu/macbundler/blob/main/CHANGELOG.md
Author-email: Shakeeb Alireza <me@example.com>
License-Expression: GPL-3.0-or-later
License-File: LICENSE
Keywords: app,bundle,codesign,dylib,dynamic-library,macos,packaging
Classifier: Development Status :: 4 - Beta
Classifier: Environment :: Console
Classifier: Environment :: MacOS X
Classifier: Intended Audience :: Developers
Classifier: License :: OSI Approved :: GNU General Public License v3 or later (GPLv3+)
Classifier: Operating System :: MacOS :: MacOS X
Classifier: Programming Language :: Python :: 3
Classifier: Programming Language :: Python :: 3.10
Classifier: Programming Language :: Python :: 3.11
Classifier: Programming Language :: Python :: 3.12
Classifier: Programming Language :: Python :: 3.13
Classifier: Topic :: Software Development :: Build Tools
Classifier: Topic :: System :: Software Distribution
Classifier: Typing :: Typed
Requires-Python: >=3.10
